[
  {
    "id": 1,
    "name": "Ollie Watkins",
    "team": "Aston Villa",
    "position": "FW",
    "detailed_position": "FW",
    "number": 0,
    "age": 0,
    "nationality": "gb-eng",
    "appearances": 6,
    "goals": 0,
    "assists": 0
  },
  {
    "id": 2,
    "name": "Morgan Rogers",
    "team": "Aston Villa",
    "position": "MF",
    "detailed_position": "FW,MF",
    "number": 0,
    "age": 0,
    "nationality": "gb-eng",
    "appearances": 6,
    "goals": 0,
    "assists": 0
  },
  {
    "id": 3,
    "name": "Matty Cash",
    "team": "Aston Villa",
    "position": "DF",
    "detailed_position": "DF",
    "number": 0,
    "age": 0,
    "nationality": "pl",
    "appearances": 6,
    "goals": 0,
    "assists": 0
  },
  {
    "id": 4,
    "name": "Tyrone Mings",
    "team": "Aston Villa",
    "position": "DF",
    "detailed_position": "DF",
    "number": 0,
    "age": 0,
    "nationality": "gb-eng",
    "appearances": 6,
    "goals": 0,
    "assists": 0
  },
  {
    "id": 5,
    "name": "John McGinn",
    "team": "Aston Villa",
    "position": "MF",
    "detailed_position": "MF,FW",
    "number": 0,
    "age": 0,
    "nationality": "gb-sct",
    "appearances": 6,
    "goals": 0,
    "assists": 0
  },
  {
    "id": 6,
    "name": "Ezri Konsa",
    "team": "Aston Villa",
    "position": "DF",
    "detailed_position": "DF",
    "number": 0,
    "age": 0,
    "nationality": "gb-eng",
    "appearances": 5,
    "goals": 0,
    "assists": 0
  },
  {
    "id": 7,
    "name": "Lucas Digne",
    "team": "Aston Villa",
    "position": "DF",
    "detailed_position": "DF",
    "number": 0,
    "age": 0,
    "nationality": "fr",
    "appearances": 6,
    "goals": 0,
    "assists": 0
  },
  {
    "id": 8,
    "name": "Emiliano Martínez",
    "team": "Aston Villa",
    "position": "GK",
    "detailed_position": "GK",
    "number": 0,
    "age": 0,
    "nationality": "ar",
    "appearances": 4,
    "goals": 0,
    "assists": 0
  },
  {
    "id": 9,
    "name": "Youri Tielemans",
    "team": "Aston Villa",
    "position": "MF",
    "detailed_position": "MF",
    "number": 0,
    "age": 0,
    "nationality": "be",
    "appearances": 4,
    "goals": 0,
    "assists": 0
  },
  {
    "id": 10,
    "name": "Evann Guessand",
    "team": "Aston Villa",
    "position": "FW",
    "detailed_position": "FW",
    "number": 0,
    "age": 0,
    "nationality": "ci",
    "appearances": 5,
    "goals": 0,
    "assists": 0
  },
  {
    "id": 11,
    "name": "Boubacar Kamara",
    "team": "Aston Villa",
    "position": "DF",
    "detailed_position": "MF,DF",
    "number": 0,
    "age": 0,
    "nationality": "fr",
    "appearances": 4,
    "goals": 0,
    "assists": 0
  },
  {
    "id": 12,
    "name": "Emi Buendía",
    "team": "Aston Villa",
    "position": "MF",
    "detailed_position": "MF,FW",
    "number": 0,
    "age": 0,
    "nationality": "ar",
    "appearances": 5,
    "goals": 0,
    "assists": 0
  },
  {
    "id": 13,
    "name": "Lamare Bogarde",
    "team": "Aston Villa",
    "position": "MF",
    "detailed_position": "MF",
    "number": 0,
    "age": 0,
    "nationality": "nl",
    "appearances": 5,
    "goals": 0,
    "assists": 0
  },
  {
    "id": 14,
    "name": "Marco Bizot",
    "team": "Aston Villa",
    "position": "GK",
    "detailed_position": "GK",
    "number": 0,
    "age": 0,
    "nationality": "nl",
    "appearances": 2,
    "goals": 0,
    "assists": 0
  },
  {
    "id": 15,
    "name": "Amadou Onana",
    "team": "Aston Villa",
    "position": "MF",
    "detailed_position": "MF",
    "number": 0,
    "age": 0,
    "nationality": "be",
    "appearances": 2,
    "goals": 0,
    "assists": 0
  },
  {
    "id": 16,
    "name": "Pau Torres",
    "team": "Aston Villa",
    "position": "DF",
    "detailed_position": "DF",
    "number": 0,
    "age": 0,
    "nationality": "es",
    "appearances": 3,
    "goals": 0,
    "assists": 0
  },
  {
    "id": 17,
    "name": "Donyell Malen",
    "team": "Aston Villa",
    "position": "MF",
    "detailed_position": "FW,MF",
    "number": 0,
    "age": 0,
    "nationality": "nl",
    "appearances": 6,
    "goals": 0,
    "assists": 0
  },
  {
    "id": 18,
    "name": "Ian Maatsen",
    "team": "Aston Villa",
    "position": "DF",
    "detailed_position": "DF",
    "number": 0,
    "age": 0,
    "nationality": "nl",
    "appearances": 3,
    "goals": 0,
    "assists": 0
  },
  {
    "id": 19,
    "name": "Harvey Elliott",
    "team": "Aston Villa",
    "position": "MF",
    "detailed_position": "MF,FW",
    "number": 0,
    "age": 0,
    "nationality": "gb-eng",
    "appearances": 3,
    "goals": 0,
    "assists": 0
  },
  {
    "id": 20,
    "name": "Victor Lindelöf",
    "team": "Aston Villa",
    "position": "MF",
    "detailed_position": "MF",
    "number": 0,
    "age": 0,
    "nationality": "se",
    "appearances": 2,
    "goals": 0,
    "assists": 0
  },
  {
    "id": 21,
    "name": "Bradley Paul Burrowes",
    "team": "Aston Villa",
    "position": "DF",
    "detailed_position": "DF",
    "number": 0,
    "age": 0,
    "nationality": "gb-eng",
    "appearances": 1,
    "goals": 0,
    "assists": 0
  },
  {
    "id": 22,
    "name": "Jadon Sancho",
    "team": "Aston Villa",
    "position": "FW",
    "detailed_position": "FW",
    "number": 0,
    "age": 0,
    "nationality": "gb-eng",
    "appearances": 1,
    "goals": 0,
    "assists": 0
  },
  {
    "id": 23,
    "name": "Samuel Iling-Junior",
    "team": "Aston Villa",
    "position": "DF",
    "detailed_position": "DF",
    "number": 0,
    "age": 0,
    "nationality": "gb-eng",
    "appearances": 0,
    "goals": 0,
    "assists": 0
  },
  {
    "id": 24,
    "name": "Jamaldeen Jimoh",
    "team": "Aston Villa",
    "position": "MF",
    "detailed_position": "MF",
    "number": 0,
    "age": 0,
    "nationality": "gb-eng",
    "appearances": 0,
    "goals": 0,
    "assists": 0
  },
  {
    "id": 25,
    "name": "Travis Patterson",
    "team": "Aston Villa",
    "position": "DF",
    "detailed_position": "DF",
    "number": 0,
    "age": 0,
    "nationality": "gb-eng",
    "appearances": 0,
    "goals": 0,
    "assists": 0
  },
  {
    "id": 26,
    "name": "Sam Proctor",
    "team": "Aston Villa",
    "position": "GK",
    "detailed_position": "GK",
    "number": 0,
    "age": 0,
    "nationality": "gb-eng",
    "appearances": 0,
    "goals": 0,
    "assists": 0
  },
  {
    "id": 27,
    "name": "Triston Rowe",
    "team": "Aston Villa",
    "position": "DF",
    "detailed_position": "DF",
    "number": 0,
    "age": 0,
    "nationality": "gb-eng",
    "appearances": 0,
    "goals": 0,
    "assists": 0
  },
  {
    "id": 28,
    "name": "James Wright",
    "team": "Aston Villa",
    "position": "GK",
    "detailed_position": "GK",
    "number": 0,
    "age": 0,
    "nationality": "gb-eng",
    "appearances": 0,
    "goals": 0,
    "assists": 0
  }
]